freecad/i10g/__init__.py
freecad/i10g/commands.py
freecad/i10g/i10g.py
freecad/i10g/init_gui.py
freecad/i10g/reload.py
freecad/i10g/version.py
freecad/i10g/resources/abort.svg
freecad/i10g/resources/add.svg
freecad/i10g/resources/animation.svg
freecad/i10g/resources/copy.svg
freecad/i10g/resources/first.svg
freecad/i10g/resources/gif.svg
freecad/i10g/resources/i10g.svg
freecad/i10g/resources/last.svg
freecad/i10g/resources/next.svg
freecad/i10g/resources/pause.svg
freecad/i10g/resources/play.svg
freecad/i10g/resources/png.svg
freecad/i10g/resources/prev.svg
freecad/i10g/resources/reload.svg
freecad/i10g/resources/remove.svg
freecad/i10g/resources/selected_step.svg
freecad/i10g/resources/step.svg
freecad/i10g/resources/update.svg
freecad/i10g/resources/video.svg
freecad.i10g-0.0.1.dist-info/LICENSE
freecad.i10g-0.0.1.dist-info/METADATA
freecad.i10g-0.0.1.dist-info/WHEEL
freecad.i10g-0.0.1.dist-info/top_level.txt
freecad.i10g-0.0.1.dist-info/RECORD
