Metadata-Version: 2.1
Name: freecad.i10g
Version: 0.0.1
Summary: FreeCAD Simple Animation Workbench
Home-page: https://github.com/anderson-/inbetweening
Maintainer: Anderson Antunes
Maintainer-email: anderson.utf@gmail.com
License: UNKNOWN
Platform: UNKNOWN
Requires-Dist: numpy
